<?xml version="1.0" encoding="UTF-8"?>
<AssetDeclaration xmlns="uri:ea.com:eala:asset" xmlns:xsi="http://www.w3.org/2001/XMLSchema-instance">
  <Tags></Tags>
  <Includes>
  </Includes>

  <!-- ZOCOMPowerPlant  = 7  seconds Power = 20 -->
  <!-- ZOCOMRefinery    = 30 seconds Power = 15 -->
  <!-- ZOCOMBarracks    = 5  seconds Power = 5 -->
  <!-- ZOCOMWarFactory  = 20 seconds Power = 7 -->
  <!-- ZOCOMCommandPost = 15 seconds Power = 9 -->
  <!-- ZOCOMAirfield    = 10 seconds Power = 8 -->
  <!-- ZOCOMMedicalBay  = 10 seconds Power = 7 -->
  <!-- ZOCOMArmory      = 40 seconds Power = 12 -->
  <!-- ZOCOMCrane       = 15 seconds Power = 10 -->

  <SkirmishOpeningMove
    id="ZOCOM_EASY"
    Side="ZOCOM">
    <Order Build="ZOCOMPowerPlant" />
    <Order Build="ZOCOMBarracks" />
    <Order Build="ZOCOMRefinery" />

    <Order Build="ZOCOMRifleSoldierSquad" />
    <Order Build="ZOCOMRifleSoldierSquad" />
    <Order Build="ZOCOMRifleSoldierSquad" />
    
    <Order Build="ZOCOMRifleSoldierSquad" />
    <Order Build="ZOCOMRifleSoldierSquad" />
    <Order Build="ZOCOMRifleSoldierSquad" />

    <Order Build="ZOCOMRifleSoldierSquad" />
    <Order Build="ZOCOMRifleSoldierSquad" />
    <Order Build="ZOCOMRifleSoldierSquad" />

    <Order Build="ZOCOMRifleSoldierSquad" />
    <Order Build="ZOCOMRifleSoldierSquad" />
    <Order Build="ZOCOMRifleSoldierSquad" />
    <Order Time="160s"/>
    <Order Build="ZOCOMWarfactory" />
    <Order Time="180s" />
  </SkirmishOpeningMove>

  <SkirmishOpeningMove
    id="ZOCOMStandard"
    Side="ZOCOM">
    <Order Build="ZOCOMPowerPlant" />
    <Order Build="ZOCOMBarracks" />
    <Order Time="12s" Account="PRODUCTION" Deposit="1500" />
    <Order Build="ZOCOMRefinery" />
    <Order Build="ZOCOMWarfactory" />
    <Order Build="ZOCOMHarvester" />
    <Order Build="ZOCOMHarvester" />
	<!-- 94s -->
    <Order Time="99s" />
    <Order Build="ZOCOMPowerPlant" />
    <Order Build="ZOCOMRefinery" />
    <Order Time="139s" />
    <Order Build="ZOCOMAPC" />
    <Order Build="ZOCOMAPC" />
    <Order Time="153s" />
    <Order Build="ZOCOMPowerPlant" />
    <Order Build="ZOCOMHarvester" />
    <Order Time="169s" />
  </SkirmishOpeningMove>
  

  <SkirmishOpeningMove
    id="ZOCOMBrutalCrane"
    Side="ZOCOM">
    <Order Build="ZOCOMPowerPlant" />
    <Order Build="ZOCOMBarracks" />
    <Order Time="12s" Account="PRODUCTION" Deposit="2500" />
    <Order Build="ZOCOMRefinery" />
    <Order Build="ZOCOMWarfactory" />
    <Order Build="ZOCOMPowerPlant" />
    <Order Build="ZOCOMHarvester" />
    <Order Build="ZOCOMHarvester" />
	<!-- 94s -->
    <Order Time="94s" />
    <Order Build="ZOCOMRefinery" />
    <Order Build="ZOCOMAPC" />
    <Order Build="ZOCOMAPC" />
    <Order Build="ZOCOMAPC" />
    <Order Build="ZOCOMHarvester" />
    <Order Build="ZOCOMPowerPlant" />
    <Order Time="131s" />
  </SkirmishOpeningMove>

<!--
  <SkirmishOpeningMove
    id="ZOCOMBrutalCrane"
    Side="ZOCOM">
    <Order Build="ZOCOMPowerPlant" />
    <Order Build="ZOCOMBarracks" />
    <Order Build="ZOCOMRefinery" />
    <Order Build="ZOCOMCrane" />
    <Order Build="ZOCOMPowerPlant" />
    <Order Build="ZOCOMRefinery" />
    <Order Build="ZOCOMWarfactory" />
    <Order Time="84s" Account="PRODUCTION" Deposit="999999" />
    <Order Build="ZOCOMPowerPlant" />
    <Order Build="ZOCOMPowerPlant" />
    <Order Build="ZOCOMRefinery" />
    <Order Build="ZOCOMPowerPlant" />
    <Order Build="ZOCOMWarfactory" />
    <Order Build="ZOCOMBarracks" />
    <Order Time="150s" />
  </SkirmishOpeningMove>
-->
</AssetDeclaration>